streamlit_mubadala_threedviewer/__init__.py
streamlit_mubadala_threedviewer/example.py
streamlit_mubadala_threedviewer/frontend/build/asset-manifest.json
streamlit_mubadala_threedviewer/frontend/build/favicon.ico
streamlit_mubadala_threedviewer/frontend/build/index.html
streamlit_mubadala_threedviewer/frontend/build/logo192.png
streamlit_mubadala_threedviewer/frontend/build/logo512.png
streamlit_mubadala_threedviewer/frontend/build/manifest.json
streamlit_mubadala_threedviewer/frontend/build/robots.txt
streamlit_mubadala_threedviewer/frontend/build/static/css/main.4efb37a3.css
streamlit_mubadala_threedviewer/frontend/build/static/js/206.4d185342.chunk.js
streamlit_mubadala_threedviewer/frontend/build/static/js/main.29eda9d4.js
streamlit_mubadala_threedviewer/frontend/build/static/js/main.29eda9d4.js.LICENSE.txt
streamlit_mubadala_threedviewer/models/__init__.py
streamlit_mubadala_threedviewer/models/beacon.py
streamlit_mubadala_threedviewer/models/camera.py
streamlit_mubadala_threedviewer/models/deck.py
streamlit_mubadala_threedviewer/models/viewer_data.py
streamlit_mubadala_threedviewer-1.0.0.dist-info/LICENSE
streamlit_mubadala_threedviewer-1.0.0.dist-info/METADATA
streamlit_mubadala_threedviewer-1.0.0.dist-info/WHEEL
streamlit_mubadala_threedviewer-1.0.0.dist-info/top_level.txt
streamlit_mubadala_threedviewer-1.0.0.dist-info/RECORD
